{ 
    "_id" : ObjectId("5af3a84b897b43287b03c46e"), 
    "inboxId" : ObjectId("5aec7a36da33f7382b1bcca7"), 
    "send_userId" : ObjectId("5ad2d8a7abf77f302343705b"), 
    "receive_userId" : ObjectId("5ad2d843abf77f3023437055"), 
    "content" : "q", 
    "isRead" : true, 
    "isActive" : true, 
    "createdAt" : ISODate("2018-05-10T02:02:51.779+0000"), 
    "updatedAt" : ISODate("2018-05-10T02:02:54.963+0000")
}
{ 
    "_id" : ObjectId("5af3acd2897b43287b03c46f"), 
    "inboxId" : ObjectId("5aec7a36da33f7382b1bcca7"), 
    "send_userId" : ObjectId("5ad2d8a7abf77f302343705b"), 
    "receive_userId" : ObjectId("5ad2d843abf77f3023437055"), 
    "content" : "Hôm nay đi học không ", 
    "isRead" : true, 
    "isActive" : true, 
    "createdAt" : ISODate("2018-05-10T02:22:10.130+0000"), 
    "updatedAt" : ISODate("2018-05-10T02:55:21.457+0000")
}
{ 
    "_id" : ObjectId("5af3b4916f2ef03c2c306014"), 
    "inboxId" : ObjectId("5aec869a738c5a582eb29408"), 
    "send_userId" : ObjectId("5ad2d8baabf77f302343705c"), 
    "receive_userId" : ObjectId("5ad2d843abf77f3023437055"), 
    "content" : "ê", 
    "isRead" : true, 
    "isActive" : true, 
    "createdAt" : ISODate("2018-05-10T02:55:13.083+0000"), 
    "updatedAt" : ISODate("2018-05-10T02:55:20.746+0000")
}
{ 
    "_id" : ObjectId("5af3b5436f2ef03c2c306015"), 
    "inboxId" : ObjectId("5aec869a738c5a582eb29408"), 
    "send_userId" : ObjectId("5ad2d8baabf77f302343705c"), 
    "receive_userId" : ObjectId("5ad2d843abf77f3023437055"), 
    "content" : "m đâu rồi", 
    "isRead" : true, 
    "isActive" : true, 
    "createdAt" : ISODate("2018-05-10T02:58:11.098+0000"), 
    "updatedAt" : ISODate("2018-05-10T03:02:07.505+0000")
}
{ 
    "_id" : ObjectId("5af3b6276f2ef03c2c306016"), 
    "inboxId" : ObjectId("5aec869a738c5a582eb29408"), 
    "send_userId" : ObjectId("5ad2d8baabf77f302343705c"), 
    "receive_userId" : ObjectId("5ad2d843abf77f3023437055"), 
    "content" : "Hôm nay không lên trường à ", 
    "isRead" : true, 
    "isActive" : true, 
    "createdAt" : ISODate("2018-05-10T03:01:59.681+0000"), 
    "updatedAt" : ISODate("2018-05-10T03:02:07.505+0000")
}
{ 
    "_id" : ObjectId("5af3b6376f2ef03c2c306017"), 
    "inboxId" : ObjectId("5aec869a738c5a582eb29408"), 
    "send_userId" : ObjectId("5ad2d843abf77f3023437055"), 
    "receive_userId" : ObjectId("5ad2d8baabf77f302343705c"), 
    "content" : "Hôm nay t nghỉ ở nhà thôi, sao thế ? ", 
    "isRead" : true, 
    "isActive" : true, 
    "createdAt" : ISODate("2018-05-10T03:02:15.921+0000"), 
    "updatedAt" : ISODate("2018-05-10T03:02:24.696+0000")
}
{ 
    "_id" : ObjectId("5af3b64c6f2ef03c2c306018"), 
    "inboxId" : ObjectId("5aec869a738c5a582eb29408"), 
    "send_userId" : ObjectId("5ad2d843abf77f3023437055"), 
    "receive_userId" : ObjectId("5ad2d8baabf77f302343705c"), 
    "content" : "Ăn cơm chưa ?", 
    "isRead" : true, 
    "isActive" : true, 
    "createdAt" : ISODate("2018-05-10T03:02:36.912+0000"), 
    "updatedAt" : ISODate("2018-05-10T03:03:44.345+0000")
}
{ 
    "_id" : ObjectId("5af3b69c6f2ef03c2c306019"), 
    "inboxId" : ObjectId("5aec869a738c5a582eb29408"), 
    "send_userId" : ObjectId("5ad2d8baabf77f302343705c"), 
    "receive_userId" : ObjectId("5ad2d843abf77f3023437055"), 
    "content" : "Ăn xong từ bao giờ rồi, lên công ty làm rồi mà chán quá ", 
    "isRead" : true, 
    "isActive" : true, 
    "createdAt" : ISODate("2018-05-10T03:03:56.377+0000"), 
    "updatedAt" : ISODate("2018-05-10T03:04:00.739+0000")
}
{ 
    "_id" : ObjectId("5af3b6b06f2ef03c2c30601a"), 
    "inboxId" : ObjectId("5aec869a738c5a582eb29408"), 
    "send_userId" : ObjectId("5ad2d843abf77f3023437055"), 
    "receive_userId" : ObjectId("5ad2d8baabf77f302343705c"), 
    "content" : "Uhm thế thôi làm tiếp đi.. t cũng phải làm thôi ", 
    "isRead" : true, 
    "isActive" : true, 
    "createdAt" : ISODate("2018-05-10T03:04:16.465+0000"), 
    "updatedAt" : ISODate("2018-05-10T03:08:36.162+0000")
}
{ 
    "_id" : ObjectId("5af3b6b46f2ef03c2c30601b"), 
    "inboxId" : ObjectId("5aec869a738c5a582eb29408"), 
    "send_userId" : ObjectId("5ad2d843abf77f3023437055"), 
    "receive_userId" : ObjectId("5ad2d8baabf77f302343705c"), 
    "content" : "Xong hết rồi ", 
    "isRead" : true, 
    "isActive" : true, 
    "createdAt" : ISODate("2018-05-10T03:04:20.145+0000"), 
    "updatedAt" : ISODate("2018-05-10T03:08:36.162+0000")
}
{ 
    "_id" : ObjectId("5af3b7c26f2ef03c2c30601c"), 
    "inboxId" : ObjectId("5aec869a738c5a582eb29408"), 
    "send_userId" : ObjectId("5ad2d8baabf77f302343705c"), 
    "receive_userId" : ObjectId("5ad2d843abf77f3023437055"), 
    "content" : "Ok nhé, t cũng nhận meesssage trên title rồi. ", 
    "isRead" : true, 
    "isActive" : true, 
    "createdAt" : ISODate("2018-05-10T03:08:50.633+0000"), 
    "updatedAt" : ISODate("2018-05-10T03:09:08.922+0000")
}
{ 
    "_id" : ObjectId("5af3b8b66f2ef03c2c30601d"), 
    "inboxId" : ObjectId("5af268a0b96c25a8283a4378"), 
    "send_userId" : ObjectId("5ad2d92fabf77f3023437061"), 
    "receive_userId" : ObjectId("5ad2d843abf77f3023437055"), 
    "content" : "Hello gúy", 
    "isRead" : true, 
    "isActive" : true, 
    "createdAt" : ISODate("2018-05-10T03:12:54.304+0000"), 
    "updatedAt" : ISODate("2018-05-10T03:13:03.528+0000")
}
{ 
    "_id" : ObjectId("5af3b8cf6f2ef03c2c30601e"), 
    "inboxId" : ObjectId("5af268a0b96c25a8283a4378"), 
    "send_userId" : ObjectId("5ad2d843abf77f3023437055"), 
    "receive_userId" : ObjectId("5ad2d92fabf77f3023437061"), 
    "content" : "Đầy dủ ", 
    "isRead" : true, 
    "isActive" : true, 
    "createdAt" : ISODate("2018-05-10T03:13:19.193+0000"), 
    "updatedAt" : ISODate("2018-05-10T03:13:27.017+0000")
}
{ 
    "_id" : ObjectId("5af3b8db6f2ef03c2c30601f"), 
    "inboxId" : ObjectId("5af268a0b96c25a8283a4378"), 
    "send_userId" : ObjectId("5ad2d92fabf77f3023437061"), 
    "receive_userId" : ObjectId("5ad2d843abf77f3023437055"), 
    "content" : "1", 
    "isRead" : true, 
    "isActive" : true, 
    "createdAt" : ISODate("2018-05-10T03:13:31.346+0000"), 
    "updatedAt" : ISODate("2018-05-10T03:14:18.529+0000")
}
{ 
    "_id" : ObjectId("5af3b8dc6f2ef03c2c306020"), 
    "inboxId" : ObjectId("5af268a0b96c25a8283a4378"), 
    "send_userId" : ObjectId("5ad2d92fabf77f3023437061"), 
    "receive_userId" : ObjectId("5ad2d843abf77f3023437055"), 
    "content" : "2", 
    "isRead" : true, 
    "isActive" : true, 
    "createdAt" : ISODate("2018-05-10T03:13:32.024+0000"), 
    "updatedAt" : ISODate("2018-05-10T03:14:18.529+0000")
}
{ 
    "_id" : ObjectId("5af3b8dc6f2ef03c2c306021"), 
    "inboxId" : ObjectId("5af268a0b96c25a8283a4378"), 
    "send_userId" : ObjectId("5ad2d92fabf77f3023437061"), 
    "receive_userId" : ObjectId("5ad2d843abf77f3023437055"), 
    "content" : "3", 
    "isRead" : true, 
    "isActive" : true, 
    "createdAt" : ISODate("2018-05-10T03:13:32.600+0000"), 
    "updatedAt" : ISODate("2018-05-10T03:14:18.529+0000")
}
{ 
    "_id" : ObjectId("5af3b8e66f2ef03c2c306022"), 
    "inboxId" : ObjectId("5af268a0b96c25a8283a4378"), 
    "send_userId" : ObjectId("5ad2d843abf77f3023437055"), 
    "receive_userId" : ObjectId("5ad2d92fabf77f3023437061"), 
    "content" : "ok", 
    "isRead" : true, 
    "isActive" : true, 
    "createdAt" : ISODate("2018-05-10T03:13:42.752+0000"), 
    "updatedAt" : ISODate("2018-05-10T03:14:15.456+0000")
}
{ 
    "_id" : ObjectId("5af3b8ee6f2ef03c2c306023"), 
    "inboxId" : ObjectId("5af268a0b96c25a8283a4378"), 
    "send_userId" : ObjectId("5ad2d843abf77f3023437055"), 
    "receive_userId" : ObjectId("5ad2d92fabf77f3023437061"), 
    "content" : "ok", 
    "isRead" : true, 
    "isActive" : true, 
    "createdAt" : ISODate("2018-05-10T03:13:50.288+0000"), 
    "updatedAt" : ISODate("2018-05-10T03:14:15.456+0000")
}
{ 
    "_id" : ObjectId("5af3b9236f2ef03c2c306024"), 
    "inboxId" : ObjectId("5af268a0b96c25a8283a4378"), 
    "send_userId" : ObjectId("5ad2d843abf77f3023437055"), 
    "receive_userId" : ObjectId("5ad2d92fabf77f3023437061"), 
    "content" : "ok", 
    "isRead" : true, 
    "isActive" : true, 
    "createdAt" : ISODate("2018-05-10T03:14:43.489+0000"), 
    "updatedAt" : ISODate("2018-05-10T03:14:55.233+0000")
}
{ 
    "_id" : ObjectId("5af3b9246f2ef03c2c306025"), 
    "inboxId" : ObjectId("5af268a0b96c25a8283a4378"), 
    "send_userId" : ObjectId("5ad2d843abf77f3023437055"), 
    "receive_userId" : ObjectId("5ad2d92fabf77f3023437061"), 
    "content" : "ok", 
    "isRead" : true, 
    "isActive" : true, 
    "createdAt" : ISODate("2018-05-10T03:14:44.881+0000"), 
    "updatedAt" : ISODate("2018-05-10T03:14:55.233+0000")
}
{ 
    "_id" : ObjectId("5af3b9276f2ef03c2c306026"), 
    "inboxId" : ObjectId("5af268a0b96c25a8283a4378"), 
    "send_userId" : ObjectId("5ad2d843abf77f3023437055"), 
    "receive_userId" : ObjectId("5ad2d92fabf77f3023437061"), 
    "content" : "1", 
    "isRead" : true, 
    "isActive" : true, 
    "createdAt" : ISODate("2018-05-10T03:14:47.568+0000"), 
    "updatedAt" : ISODate("2018-05-10T03:14:55.233+0000")
}
{ 
    "_id" : ObjectId("5af3b9286f2ef03c2c306027"), 
    "inboxId" : ObjectId("5af268a0b96c25a8283a4378"), 
    "send_userId" : ObjectId("5ad2d843abf77f3023437055"), 
    "receive_userId" : ObjectId("5ad2d92fabf77f3023437061"), 
    "content" : "2", 
    "isRead" : true, 
    "isActive" : true, 
    "createdAt" : ISODate("2018-05-10T03:14:48.665+0000"), 
    "updatedAt" : ISODate("2018-05-10T03:14:55.233+0000")
}
{ 
    "_id" : ObjectId("5af3b9296f2ef03c2c306028"), 
    "inboxId" : ObjectId("5af268a0b96c25a8283a4378"), 
    "send_userId" : ObjectId("5ad2d843abf77f3023437055"), 
    "receive_userId" : ObjectId("5ad2d92fabf77f3023437061"), 
    "content" : "3", 
    "isRead" : true, 
    "isActive" : true, 
    "createdAt" : ISODate("2018-05-10T03:14:49.761+0000"), 
    "updatedAt" : ISODate("2018-05-10T03:14:55.233+0000")
}
{ 
    "_id" : ObjectId("5af3b9ef6f2ef03c2c306029"), 
    "inboxId" : ObjectId("5af26b12b96c25a8283a439f"), 
    "send_userId" : ObjectId("5ad2d92fabf77f3023437061"), 
    "receive_userId" : ObjectId("5ad2d8baabf77f302343705c"), 
    "content" : "biển ơi ", 
    "isRead" : false, 
    "isActive" : true, 
    "createdAt" : ISODate("2018-05-10T03:18:07.832+0000"), 
    "updatedAt" : ISODate("2018-05-10T03:18:07.832+0000")
}
{ 
    "_id" : ObjectId("5af3b9f66f2ef03c2c30602a"), 
    "inboxId" : ObjectId("5af268a0b96c25a8283a4378"), 
    "send_userId" : ObjectId("5ad2d92fabf77f3023437061"), 
    "receive_userId" : ObjectId("5ad2d843abf77f3023437055"), 
    "content" : "biển ơi ", 
    "isRead" : true, 
    "isActive" : true, 
    "createdAt" : ISODate("2018-05-10T03:18:14.536+0000"), 
    "updatedAt" : ISODate("2018-05-10T03:20:38.120+0000")
}
{ 
    "_id" : ObjectId("5af3ba956f2ef03c2c30602b"), 
    "inboxId" : ObjectId("5af268a0b96c25a8283a4378"), 
    "send_userId" : ObjectId("5ad2d92fabf77f3023437061"), 
    "receive_userId" : ObjectId("5ad2d843abf77f3023437055"), 
    "content" : "Tý đi ăn cơm không ", 
    "isRead" : true, 
    "isActive" : true, 
    "createdAt" : ISODate("2018-05-10T03:20:53.097+0000"), 
    "updatedAt" : ISODate("2018-05-10T03:22:44.712+0000")
}
{ 
    "_id" : ObjectId("5af66fa9d3e5d2141a8b5a72"), 
    "inboxId" : ObjectId("5af268a0b96c25a8283a4378"), 
    "send_userId" : ObjectId("5ad2d92fabf77f3023437061"), 
    "receive_userId" : ObjectId("5ad2d843abf77f3023437055"), 
    "content" : "alo", 
    "isRead" : true, 
    "isActive" : true, 
    "createdAt" : ISODate("2018-05-12T04:38:01.093+0000"), 
    "updatedAt" : ISODate("2018-05-12T04:49:00.865+0000")
}
{ 
    "_id" : ObjectId("5af67056d3e5d2141a8b5ac7"), 
    "inboxId" : ObjectId("5af6702dd3e5d2141a8b5a85"), 
    "send_userId" : ObjectId("5ad2d910abf77f302343705f"), 
    "receive_userId" : ObjectId("5af66ff1d3e5d2141a8b5a73"), 
    "content" : "an com chua em oi ", 
    "isRead" : true, 
    "isActive" : true, 
    "createdAt" : ISODate("2018-05-12T04:40:54.202+0000"), 
    "updatedAt" : ISODate("2018-05-12T04:40:58.944+0000")
}
{ 
    "_id" : ObjectId("5af6705fd3e5d2141a8b5ac8"), 
    "inboxId" : ObjectId("5af6702dd3e5d2141a8b5a85"), 
    "send_userId" : ObjectId("5ad2d910abf77f302343705f"), 
    "receive_userId" : ObjectId("5af66ff1d3e5d2141a8b5a73"), 
    "content" : "thay gi chua", 
    "isRead" : true, 
    "isActive" : true, 
    "createdAt" : ISODate("2018-05-12T04:41:03.345+0000"), 
    "updatedAt" : ISODate("2018-05-12T04:41:08.561+0000")
}
{ 
    "_id" : ObjectId("5af67060d3e5d2141a8b5ac9"), 
    "inboxId" : ObjectId("5af6702dd3e5d2141a8b5a85"), 
    "send_userId" : ObjectId("5af66ff1d3e5d2141a8b5a73"), 
    "receive_userId" : ObjectId("5ad2d910abf77f302343705f"), 
    "content" : "e chưa a ơi", 
    "isRead" : true, 
    "isActive" : true, 
    "createdAt" : ISODate("2018-05-12T04:41:04.941+0000"), 
    "updatedAt" : ISODate("2018-05-12T05:07:00.149+0000")
}
{ 
    "_id" : ObjectId("5af67065d3e5d2141a8b5aca"), 
    "inboxId" : ObjectId("5af6702dd3e5d2141a8b5a85"), 
    "send_userId" : ObjectId("5ad2d910abf77f302343705f"), 
    "receive_userId" : ObjectId("5af66ff1d3e5d2141a8b5a73"), 
    "content" : "the an di ", 
    "isRead" : true, 
    "isActive" : true, 
    "createdAt" : ISODate("2018-05-12T04:41:09.333+0000"), 
    "updatedAt" : ISODate("2018-05-12T04:55:32.875+0000")
}
{ 
    "_id" : ObjectId("5af67067d3e5d2141a8b5acb"), 
    "inboxId" : ObjectId("5af6702dd3e5d2141a8b5a85"), 
    "send_userId" : ObjectId("5af66ff1d3e5d2141a8b5a73"), 
    "receive_userId" : ObjectId("5ad2d910abf77f302343705f"), 
    "content" : "ok", 
    "isRead" : true, 
    "isActive" : true, 
    "createdAt" : ISODate("2018-05-12T04:41:11.990+0000"), 
    "updatedAt" : ISODate("2018-05-12T05:07:00.149+0000")
}
{ 
    "_id" : ObjectId("5af67242d3e5d2141a8b5acc"), 
    "inboxId" : ObjectId("5af268a0b96c25a8283a4378"), 
    "send_userId" : ObjectId("5ad2d843abf77f3023437055"), 
    "receive_userId" : ObjectId("5ad2d92fabf77f3023437061"), 
    "content" : "hello ", 
    "isRead" : false, 
    "isActive" : true, 
    "createdAt" : ISODate("2018-05-12T04:49:06.193+0000"), 
    "updatedAt" : ISODate("2018-05-12T04:49:06.193+0000")
}
{ 
    "_id" : ObjectId("5af67244d3e5d2141a8b5acd"), 
    "inboxId" : ObjectId("5af268a0b96c25a8283a4378"), 
    "send_userId" : ObjectId("5ad2d843abf77f3023437055"), 
    "receive_userId" : ObjectId("5ad2d92fabf77f3023437061"), 
    "content" : "Ting tin ", 
    "isRead" : false, 
    "isActive" : true, 
    "createdAt" : ISODate("2018-05-12T04:49:08.658+0000"), 
    "updatedAt" : ISODate("2018-05-12T04:49:08.658+0000")
}
{ 
    "_id" : ObjectId("5af67252d3e5d2141a8b5ace"), 
    "inboxId" : ObjectId("5af268a0b96c25a8283a4378"), 
    "send_userId" : ObjectId("5ad2d843abf77f3023437055"), 
    "receive_userId" : ObjectId("5ad2d92fabf77f3023437061"), 
    "content" : "Minh liên ko đai ca ", 
    "isRead" : false, 
    "isActive" : true, 
    "createdAt" : ISODate("2018-05-12T04:49:22.601+0000"), 
    "updatedAt" : ISODate("2018-05-12T04:49:22.601+0000")
}
{ 
    "_id" : ObjectId("5af67261d3e5d2141a8b5acf"), 
    "inboxId" : ObjectId("5af6700ed3e5d2141a8b5a75"), 
    "send_userId" : ObjectId("5ad2d843abf77f3023437055"), 
    "receive_userId" : ObjectId("5af66ff1d3e5d2141a8b5a73"), 
    "content" : "Minh liên đê ", 
    "isRead" : true, 
    "isActive" : true, 
    "createdAt" : ISODate("2018-05-12T04:49:37.409+0000"), 
    "updatedAt" : ISODate("2018-05-12T04:55:33.498+0000")
}
{ 
    "_id" : ObjectId("5af673c8d3e5d2141a8b5ad0"), 
    "inboxId" : ObjectId("5af6700ed3e5d2141a8b5a75"), 
    "send_userId" : ObjectId("5af66ff1d3e5d2141a8b5a73"), 
    "receive_userId" : ObjectId("5ad2d843abf77f3023437055"), 
    "content" : "ok :v", 
    "isRead" : true, 
    "isActive" : true, 
    "createdAt" : ISODate("2018-05-12T04:55:36.602+0000"), 
    "updatedAt" : ISODate("2018-05-12T04:55:38.953+0000")
}
{ 
    "_id" : ObjectId("5af673cdd3e5d2141a8b5ad1"), 
    "inboxId" : ObjectId("5af6700ed3e5d2141a8b5a75"), 
    "send_userId" : ObjectId("5af66ff1d3e5d2141a8b5a73"), 
    "receive_userId" : ObjectId("5ad2d843abf77f3023437055"), 
    "content" : "quất thôi", 
    "isRead" : true, 
    "isActive" : true, 
    "createdAt" : ISODate("2018-05-12T04:55:41.998+0000"), 
    "updatedAt" : ISODate("2018-05-12T04:55:58.778+0000")
}
{ 
    "_id" : ObjectId("5af673d3d3e5d2141a8b5ad2"), 
    "inboxId" : ObjectId("5af6700ed3e5d2141a8b5a75"), 
    "send_userId" : ObjectId("5ad2d843abf77f3023437055"), 
    "receive_userId" : ObjectId("5af66ff1d3e5d2141a8b5a73"), 
    "content" : "mà đã thấy có ai đâu", 
    "isRead" : false, 
    "isActive" : true, 
    "createdAt" : ISODate("2018-05-12T04:55:47.177+0000"), 
    "updatedAt" : ISODate("2018-05-12T04:55:47.177+0000")
}
{ 
    "_id" : ObjectId("5af673dcd3e5d2141a8b5ad3"), 
    "inboxId" : ObjectId("5af6700ed3e5d2141a8b5a75"), 
    "send_userId" : ObjectId("5ad2d843abf77f3023437055"), 
    "receive_userId" : ObjectId("5af66ff1d3e5d2141a8b5a73"), 
    "content" : "Mấy anh bảo đánh xong nặn đâu mất =))) ", 
    "isRead" : false, 
    "isActive" : true, 
    "createdAt" : ISODate("2018-05-12T04:55:56.225+0000"), 
    "updatedAt" : ISODate("2018-05-12T04:55:56.225+0000")
}
{ 
    "_id" : ObjectId("5af6741bd3e5d2141a8b5ad8"), 
    "inboxId" : ObjectId("5af673fbd3e5d2141a8b5ad5"), 
    "send_userId" : ObjectId("5ad2d910abf77f302343705f"), 
    "receive_userId" : ObjectId("5ad2d843abf77f3023437055"), 
    "content" : "alooo", 
    "isRead" : true, 
    "isActive" : true, 
    "createdAt" : ISODate("2018-05-12T04:56:59.087+0000"), 
    "updatedAt" : ISODate("2018-05-12T04:57:02.372+0000")
}
{ 
    "_id" : ObjectId("5af6741ed3e5d2141a8b5ad9"), 
    "inboxId" : ObjectId("5af673fbd3e5d2141a8b5ad5"), 
    "send_userId" : ObjectId("5ad2d910abf77f302343705f"), 
    "receive_userId" : ObjectId("5ad2d843abf77f3023437055"), 
    "content" : "cuc cu", 
    "isRead" : true, 
    "isActive" : true, 
    "createdAt" : ISODate("2018-05-12T04:57:02.187+0000"), 
    "updatedAt" : ISODate("2018-05-12T04:57:02.372+0000")
}
{ 
    "_id" : ObjectId("5af67422d3e5d2141a8b5ada"), 
    "inboxId" : ObjectId("5af673fbd3e5d2141a8b5ad5"), 
    "send_userId" : ObjectId("5ad2d843abf77f3023437055"), 
    "receive_userId" : ObjectId("5ad2d910abf77f302343705f"), 
    "content" : "hello boy ", 
    "isRead" : true, 
    "isActive" : true, 
    "createdAt" : ISODate("2018-05-12T04:57:06.585+0000"), 
    "updatedAt" : ISODate("2018-05-12T05:06:12.413+0000")
}
{ 
    "_id" : ObjectId("5af67425d3e5d2141a8b5adb"), 
    "inboxId" : ObjectId("5af673fbd3e5d2141a8b5ad5"), 
    "send_userId" : ObjectId("5ad2d843abf77f3023437055"), 
    "receive_userId" : ObjectId("5ad2d910abf77f302343705f"), 
    "content" : "Ting Ting ", 
    "isRead" : true, 
    "isActive" : true, 
    "createdAt" : ISODate("2018-05-12T04:57:09.201+0000"), 
    "updatedAt" : ISODate("2018-05-12T05:06:12.413+0000")
}
{ 
    "_id" : ObjectId("5af6743ed3e5d2141a8b5adc"), 
    "inboxId" : ObjectId("5af673fbd3e5d2141a8b5ad5"), 
    "send_userId" : ObjectId("5ad2d843abf77f3023437055"), 
    "receive_userId" : ObjectId("5ad2d910abf77f302343705f"), 
    "content" : "Đăng ít bài đăng đi.. ", 
    "isRead" : true, 
    "isActive" : true, 
    "createdAt" : ISODate("2018-05-12T04:57:34.321+0000"), 
    "updatedAt" : ISODate("2018-05-12T05:06:12.413+0000")
}
{ 
    "_id" : ObjectId("5af67459d3e5d2141a8b5add"), 
    "inboxId" : ObjectId("5af673fbd3e5d2141a8b5ad5"), 
    "send_userId" : ObjectId("5ad2d910abf77f302343705f"), 
    "receive_userId" : ObjectId("5ad2d843abf77f3023437055"), 
    "content" : "k đăng đc bằng điện thoại à", 
    "isRead" : true, 
    "isActive" : true, 
    "createdAt" : ISODate("2018-05-12T04:58:01.852+0000"), 
    "updatedAt" : ISODate("2018-05-12T04:58:21.049+0000")
}
{ 
    "_id" : ObjectId("5af6745ad3e5d2141a8b5ade"), 
    "inboxId" : ObjectId("5af673fbd3e5d2141a8b5ad5"), 
    "send_userId" : ObjectId("5ad2d910abf77f302343705f"), 
    "receive_userId" : ObjectId("5ad2d843abf77f3023437055"), 
    "content" : ":))", 
    "isRead" : true, 
    "isActive" : true, 
    "createdAt" : ISODate("2018-05-12T04:58:02.816+0000"), 
    "updatedAt" : ISODate("2018-05-12T04:58:21.049+0000")
}
{ 
    "_id" : ObjectId("5af67466d3e5d2141a8b5adf"), 
    "inboxId" : ObjectId("5af673fbd3e5d2141a8b5ad5"), 
    "send_userId" : ObjectId("5ad2d843abf77f3023437055"), 
    "receive_userId" : ObjectId("5ad2d910abf77f302343705f"), 
    "content" : "thử xem =))) được đó.. ", 
    "isRead" : true, 
    "isActive" : true, 
    "createdAt" : ISODate("2018-05-12T04:58:14.993+0000"), 
    "updatedAt" : ISODate("2018-05-12T05:06:12.413+0000")
}
{ 
    "_id" : ObjectId("5af674ecd3e5d2141a8b5ae0"), 
    "inboxId" : ObjectId("5af673fbd3e5d2141a8b5ad5"), 
    "send_userId" : ObjectId("5ad2d843abf77f3023437055"), 
    "receive_userId" : ObjectId("5ad2d910abf77f302343705f"), 
    "content" : "Thử chưa ", 
    "isRead" : true, 
    "isActive" : true, 
    "createdAt" : ISODate("2018-05-12T05:00:28.893+0000"), 
    "updatedAt" : ISODate("2018-05-12T05:06:12.413+0000")
}
{ 
    "_id" : ObjectId("5af675acd3e5d2141a8b5aee"), 
    "inboxId" : ObjectId("5af6700ed3e5d2141a8b5a75"), 
    "send_userId" : ObjectId("5ad2d843abf77f3023437055"), 
    "receive_userId" : ObjectId("5af66ff1d3e5d2141a8b5a73"), 
    "content" : "minh liên đê bạn ", 
    "isRead" : false, 
    "isActive" : true, 
    "createdAt" : ISODate("2018-05-12T05:03:40.401+0000"), 
    "updatedAt" : ISODate("2018-05-12T05:03:40.401+0000")
}
{ 
    "_id" : ObjectId("5af67665d3e5d2141a8b5af0"), 
    "inboxId" : ObjectId("5af673fbd3e5d2141a8b5ad5"), 
    "send_userId" : ObjectId("5ad2d910abf77f302343705f"), 
    "receive_userId" : ObjectId("5ad2d843abf77f3023437055"), 
    "content" : "xem lại cái đoạn cập nhật avav đê", 
    "isRead" : true, 
    "isActive" : true, 
    "createdAt" : ISODate("2018-05-12T05:06:45.489+0000"), 
    "updatedAt" : ISODate("2018-05-12T05:07:35.658+0000")
}
{ 
    "_id" : ObjectId("5af6766fd3e5d2141a8b5af1"), 
    "inboxId" : ObjectId("5af673fbd3e5d2141a8b5ad5"), 
    "send_userId" : ObjectId("5ad2d910abf77f302343705f"), 
    "receive_userId" : ObjectId("5ad2d843abf77f3023437055"), 
    "content" : "lỗi mãi mới đc", 
    "isRead" : true, 
    "isActive" : true, 
    "createdAt" : ISODate("2018-05-12T05:06:55.311+0000"), 
    "updatedAt" : ISODate("2018-05-12T05:07:35.658+0000")
}
{ 
    "_id" : ObjectId("5af676a0d3e5d2141a8b5af8"), 
    "inboxId" : ObjectId("5af673fbd3e5d2141a8b5ad5"), 
    "send_userId" : ObjectId("5ad2d843abf77f3023437055"), 
    "receive_userId" : ObjectId("5ad2d910abf77f302343705f"), 
    "content" : "ko phair dduaa", 
    "isRead" : true, 
    "isActive" : true, 
    "createdAt" : ISODate("2018-05-12T05:07:44.114+0000"), 
    "updatedAt" : ISODate("2018-05-12T05:07:48.342+0000")
}
{ 
    "_id" : ObjectId("5af676a5d3e5d2141a8b5af9"), 
    "inboxId" : ObjectId("5af673fbd3e5d2141a8b5ad5"), 
    "send_userId" : ObjectId("5ad2d843abf77f3023437055"), 
    "receive_userId" : ObjectId("5ad2d910abf77f302343705f"), 
    "content" : "Phải đợi nó load ảnh đã chứ ", 
    "isRead" : true, 
    "isActive" : true, 
    "createdAt" : ISODate("2018-05-12T05:07:49.649+0000"), 
    "updatedAt" : ISODate("2018-05-12T05:08:18.996+0000")
}
{ 
    "_id" : ObjectId("5af676b2d3e5d2141a8b5afa"), 
    "inboxId" : ObjectId("5af673fbd3e5d2141a8b5ad5"), 
    "send_userId" : ObjectId("5ad2d910abf77f302343705f"), 
    "receive_userId" : ObjectId("5ad2d843abf77f3023437055"), 
    "content" : "nó có hiện loading đâu :)", 
    "isRead" : true, 
    "isActive" : true, 
    "createdAt" : ISODate("2018-05-12T05:08:02.721+0000"), 
    "updatedAt" : ISODate("2018-05-12T05:08:17.611+0000")
}
{ 
    "_id" : ObjectId("5af676bbd3e5d2141a8b5aff"), 
    "inboxId" : ObjectId("5af673fbd3e5d2141a8b5ad5"), 
    "send_userId" : ObjectId("5ad2d843abf77f3023437055"), 
    "receive_userId" : ObjectId("5ad2d910abf77f302343705f"), 
    "content" : "uhm.. quên ko cho hiện =))", 
    "isRead" : true, 
    "isActive" : true, 
    "createdAt" : ISODate("2018-05-12T05:08:11.104+0000"), 
    "updatedAt" : ISODate("2018-05-12T05:08:18.996+0000")
}
{ 
    "_id" : ObjectId("5af676c0d3e5d2141a8b5b00"), 
    "inboxId" : ObjectId("5af673fbd3e5d2141a8b5ad5"), 
    "send_userId" : ObjectId("5ad2d843abf77f3023437055"), 
    "receive_userId" : ObjectId("5ad2d910abf77f302343705f"), 
    "content" : "tý lấy cái react-laoding cho vào :V ", 
    "isRead" : true, 
    "isActive" : true, 
    "createdAt" : ISODate("2018-05-12T05:08:16.257+0000"), 
    "updatedAt" : ISODate("2018-05-12T05:08:18.996+0000")
}
{ 
    "_id" : ObjectId("5af676cad3e5d2141a8b5b01"), 
    "inboxId" : ObjectId("5af673fbd3e5d2141a8b5ad5"), 
    "send_userId" : ObjectId("5ad2d910abf77f302343705f"), 
    "receive_userId" : ObjectId("5ad2d843abf77f3023437055"), 
    "content" : "cho vào đê :))", 
    "isRead" : true, 
    "isActive" : true, 
    "createdAt" : ISODate("2018-05-12T05:08:26.091+0000"), 
    "updatedAt" : ISODate("2018-05-12T05:08:28.193+0000")
}
{ 
    "_id" : ObjectId("5af676d1d3e5d2141a8b5b02"), 
    "inboxId" : ObjectId("5af673fbd3e5d2141a8b5ad5"), 
    "send_userId" : ObjectId("5ad2d843abf77f3023437055"), 
    "receive_userId" : ObjectId("5ad2d910abf77f302343705f"), 
    "content" : "easy game =)))) ", 
    "isRead" : true, 
    "isActive" : true, 
    "createdAt" : ISODate("2018-05-12T05:08:33.633+0000"), 
    "updatedAt" : ISODate("2018-05-12T05:09:34.169+0000")
}
{ 
    "_id" : ObjectId("5af677c0d3e5d2141a8b5b08"), 
    "inboxId" : ObjectId("5af677a0d3e5d2141a8b5b05"), 
    "send_userId" : ObjectId("5ad2d843abf77f3023437055"), 
    "receive_userId" : ObjectId("5af6778ed3e5d2141a8b5b03"), 
    "content" : "dm TÙng ", 
    "isRead" : true, 
    "isActive" : true, 
    "createdAt" : ISODate("2018-05-12T05:12:32.568+0000"), 
    "updatedAt" : ISODate("2018-05-12T05:12:51.317+0000")
}
{ 
    "_id" : ObjectId("5af677d5d3e5d2141a8b5b09"), 
    "inboxId" : ObjectId("5af677a0d3e5d2141a8b5b05"), 
    "send_userId" : ObjectId("5ad2d843abf77f3023437055"), 
    "receive_userId" : ObjectId("5af6778ed3e5d2141a8b5b03"), 
    "content" : "rep đi xem nào ", 
    "isRead" : false, 
    "isActive" : true, 
    "createdAt" : ISODate("2018-05-12T05:12:53.161+0000"), 
    "updatedAt" : ISODate("2018-05-12T05:12:53.161+0000")
}
{ 
    "_id" : ObjectId("5af677d5d3e5d2141a8b5b0a"), 
    "inboxId" : ObjectId("5af677a0d3e5d2141a8b5b05"), 
    "send_userId" : ObjectId("5af6778ed3e5d2141a8b5b03"), 
    "receive_userId" : ObjectId("5ad2d843abf77f3023437055"), 
    "content" : "hello", 
    "isRead" : true, 
    "isActive" : true, 
    "createdAt" : ISODate("2018-05-12T05:12:53.517+0000"), 
    "updatedAt" : ISODate("2018-05-12T05:13:09.114+0000")
}
{ 
    "_id" : ObjectId("5af677d9d3e5d2141a8b5b0b"), 
    "inboxId" : ObjectId("5af677a0d3e5d2141a8b5b05"), 
    "send_userId" : ObjectId("5af6778ed3e5d2141a8b5b03"), 
    "receive_userId" : ObjectId("5ad2d843abf77f3023437055"), 
    "content" : "đm biển", 
    "isRead" : true, 
    "isActive" : true, 
    "createdAt" : ISODate("2018-05-12T05:12:57.060+0000"), 
    "updatedAt" : ISODate("2018-05-12T05:13:09.114+0000")
}
{ 
    "_id" : ObjectId("5af677dad3e5d2141a8b5b0c"), 
    "inboxId" : ObjectId("5af677a0d3e5d2141a8b5b05"), 
    "send_userId" : ObjectId("5ad2d843abf77f3023437055"), 
    "receive_userId" : ObjectId("5af6778ed3e5d2141a8b5b03"), 
    "content" : "ok girl", 
    "isRead" : false, 
    "isActive" : true, 
    "createdAt" : ISODate("2018-05-12T05:12:58.305+0000"), 
    "updatedAt" : ISODate("2018-05-12T05:12:58.305+0000")
}
